privacypass/__init__.py
privacypass/privacypass.py
privacypass/voprf.py
privacypass-0.2.2.dist-info/LICENSE
privacypass-0.2.2.dist-info/METADATA
privacypass-0.2.2.dist-info/WHEEL
privacypass-0.2.2.dist-info/top_level.txt
privacypass-0.2.2.dist-info/RECORD
