Metadata-Version: 2.1
Name: privacypass
Version: 0.2.2
Summary: Bypass Cloudflare's CAPTCHAs by redeming Privacy Pass tokens.
Home-page: https://github.com/sergebakharev/privacypass
Author: Serge Bakharev
Author-email: 
License: MIT
Keywords: cloudflare,captcha,scraping
Platform: UNKNOWN
Classifier: Intended Audience :: Developers
Classifier: Natural Language :: English
Classifier: License :: OSI Approved :: MIT License
Classifier: Programming Language :: Python :: 3.9
Requires-Python: >=3.9
License-File: LICENSE
Requires-Dist: cryptography (~=42.0.4)
